__init__.py
trashmailapi/__init__.py
trashmailapi/vsimcard.py
trashmailapi-1.1.dist-info/LICENSE
trashmailapi-1.1.dist-info/METADATA
trashmailapi-1.1.dist-info/WHEEL
trashmailapi-1.1.dist-info/top_level.txt
trashmailapi-1.1.dist-info/RECORD
