Metadata-Version: 2.1
Name: trashmailapi
Version: 1.1
Summary: Unofficial API for trash/temporary mail services in Python
Author-email: mazer <DO-NOT-EMAIL@example.com>
Project-URL: Homepage, https://codeberg.org/m3r/trashmailapi
Project-URL: Bug Tracker, https://codeberg.org/m3r/trashmailapi/issues
Classifier: Programming Language :: Python :: 3
Classifier: License :: OSI Approved :: MIT License
Classifier: Operating System :: OS Independent
Requires-Python: >=3.10
License-File: LICENSE
Requires-Dist: beautifulsoup4 (==4.12.2)
Requires-Dist: certifi (==2022.12.7)
Requires-Dist: charset-normalizer (==3.1.0)
Requires-Dist: idna (==3.4)
Requires-Dist: requests (==2.29.0)
Requires-Dist: soupsieve (==2.4.1)
Requires-Dist: urllib3 (==1.26.15)
